autoworkerz/__init__.py
autoworkerz/core.py
autoworkerz-0.1.1.dist-info/METADATA
autoworkerz-0.1.1.dist-info/WHEEL
autoworkerz-0.1.1.dist-info/top_level.txt
autoworkerz-0.1.1.dist-info/RECORD
